django_proxyblock-0.2.0.dist-info/DESCRIPTION.rst
django_proxyblock-0.2.0.dist-info/METADATA
django_proxyblock-0.2.0.dist-info/RECORD
django_proxyblock-0.2.0.dist-info/WHEEL
django_proxyblock-0.2.0.dist-info/metadata.json
django_proxyblock-0.2.0.dist-info/top_level.txt
proxyblock/__init__.py
proxyblock/models.py
