Metadata-Version: 2.0
Name: django-proxyblock
Version: 0.2.0
Summary: proxy another pageblock
Home-page: UNKNOWN
Author: Anders Pearson
Author-email: anders@columbia.edu
License: BSD
Platform: any
